Topsis/__init__.py
Topsis/topsis.py
Topsis_Ishtdeep_102003315-0.1.1.dist-info/METADATA
Topsis_Ishtdeep_102003315-0.1.1.dist-info/WHEEL
Topsis_Ishtdeep_102003315-0.1.1.dist-info/entry_points.txt
Topsis_Ishtdeep_102003315-0.1.1.dist-info/top_level.txt
Topsis_Ishtdeep_102003315-0.1.1.dist-info/RECORD
